neurograd/__init__.py
neurograd/tensor.py
neurograd/amp/__init__.py
neurograd/amp/autocast.py
neurograd/amp/grad_scaler.py
neurograd/amp/utils.py
neurograd/functions/__init__.py
neurograd/functions/activations.py
neurograd/functions/arithmetic.py
neurograd/functions/base.py
neurograd/functions/conv.py
neurograd/functions/linalg.py
neurograd/functions/math.py
neurograd/functions/normalize.py
neurograd/functions/reductions.py
neurograd/functions/tensor_ops.py
neurograd/nn/__init__.py
neurograd/nn/activations.py
neurograd/nn/factory.py
neurograd/nn/initializers.py
neurograd/nn/losses.py
neurograd/nn/metrics.py
neurograd/nn/module.py
neurograd/nn/layers/__init__.py
neurograd/nn/layers/batchnorm.py
neurograd/nn/layers/conv.py
neurograd/nn/layers/dropout.py
neurograd/nn/layers/linear.py
neurograd/optim/__init__.py
neurograd/optim/adam.py
neurograd/optim/adamw.py
neurograd/optim/optimizer.py
neurograd/optim/rmsprop.py
neurograd/optim/sgd.py
neurograd/transforms/__init__.py
neurograd/transforms/base.py
neurograd/utils/__init__.py
neurograd/utils/aliases.py
neurograd/utils/data.py
neurograd/utils/device.py
neurograd/utils/grad_check.py
neurograd/utils/graph.py
neurograd/utils/memory.py
neurograd/utils/no_grad.py
neurograd-5.3.7.dist-info/METADATA
neurograd-5.3.7.dist-info/WHEEL
neurograd-5.3.7.dist-info/top_level.txt
neurograd-5.3.7.dist-info/RECORD
