Metadata-Version: 2.1
Name: neurograd
Version: 5.3.7
Summary: A Pure Python Deep Learning Framework with Automatic Differentiation
Home-page: https://github.com/b-ionut-r/neurograd
Author: Bujor Ionut Raul
Author-email: b-ionut-r@users.noreply.github.com
Project-URL: Bug Tracker, https://github.com/b-ionut-r/neurograd/issues
Project-URL: Documentation, https://github.com/b-ionut-r/neurograd#readme
Project-URL: Repository, https://github.com/b-ionut-r/neurograd
Keywords: deep-learning,neural-networks,automatic-differentiation,machine-learning,pytorch-like,python,gpu,cuda,conv2d,backpropagation
Classifier: Development Status :: 3 - Alpha
Classifier: Intended Audience :: Developers
Classifier: Intended Audience :: Education
Classifier: Intended Audience :: Science/Research
Classifier: License :: OSI Approved :: MIT License
Classifier: Operating System :: OS Independent
Classifier: Programming Language :: Python :: 3
Classifier: Programming Language :: Python :: 3.7
Classifier: Programming Language :: Python :: 3.8
Classifier: Programming Language :: Python :: 3.9
Classifier: Programming Language :: Python :: 3.10
Classifier: Programming Language :: Python :: 3.11
Classifier: Programming Language :: Python :: 3.12
Classifier: Topic :: Scientific/Engineering :: Artificial Intelligence
Classifier: Topic :: Software Development :: Libraries :: Python Modules
Requires-Python: >=3.7
Requires-Dist: Pillow >=10.0.0
Requires-Dist: albumentations
Requires-Dist: cloudpickle >=2.0.0
Requires-Dist: multiprocess
Requires-Dist: numpy >=1.19.0
Requires-Dist: opencv-python-headless >=4.7.0
Requires-Dist: opt-einsum >=3.0.0
Provides-Extra: all
Requires-Dist: black ; extra == 'all'
Requires-Dist: cupy-cuda12x ==13.5.1 ; extra == 'all'
Requires-Dist: cuquantum-cu12 >=24.3.0 ; extra == 'all'
Requires-Dist: cuquantum-python-cu12 >=24.3.0 ; extra == 'all'
Requires-Dist: cutensor-cu12 ; extra == 'all'
Requires-Dist: datasets >=2.0.0 ; extra == 'all'
Requires-Dist: flake8 ; extra == 'all'
Requires-Dist: ipykernel >=6.0.0 ; extra == 'all'
Requires-Dist: jupyter >=1.0.0 ; extra == 'all'
Requires-Dist: matplotlib >=3.3.0 ; extra == 'all'
Requires-Dist: multiprocess >=0.70.0 ; extra == 'all'
Requires-Dist: mypy ; extra == 'all'
Requires-Dist: pytest-cov ; extra == 'all'
Requires-Dist: pytest >=6.0.0 ; extra == 'all'
Requires-Dist: scikit-learn >=0.24.0 ; extra == 'all'
Requires-Dist: nvidia-dali-cuda120 ; (platform_system == "Linux") and extra == 'all'
Provides-Extra: dev
Requires-Dist: black ; extra == 'dev'
Requires-Dist: flake8 ; extra == 'dev'
Requires-Dist: mypy ; extra == 'dev'
Requires-Dist: pytest-cov ; extra == 'dev'
Requires-Dist: pytest >=6.0.0 ; extra == 'dev'
Provides-Extra: examples
Requires-Dist: matplotlib >=3.3.0 ; extra == 'examples'
Requires-Dist: scikit-learn >=0.24.0 ; extra == 'examples'
Provides-Extra: gpu
Requires-Dist: cupy-cuda12x ==13.5.1 ; extra == 'gpu'
Requires-Dist: cuquantum-cu12 >=24.3.0 ; extra == 'gpu'
Requires-Dist: cuquantum-python-cu12 >=24.3.0 ; extra == 'gpu'
Requires-Dist: nvidia-dali-cuda120 ; (platform_system == "Linux") and extra == 'gpu'
Provides-Extra: notebooks
Requires-Dist: ipykernel >=6.0.0 ; extra == 'notebooks'
Requires-Dist: jupyter >=1.0.0 ; extra == 'notebooks'
Requires-Dist: matplotlib >=3.3.0 ; extra == 'notebooks'
Requires-Dist: scikit-learn >=0.24.0 ; extra == 'notebooks'
Provides-Extra: visualization
Requires-Dist: matplotlib >=3.3.0 ; extra == 'visualization'
